directadmin/__init__.py
directadmin/base.py
directadmin/client.py
directadmin/endpoints.py
directadmin_cli-0.1.5.dist-info/METADATA
directadmin_cli-0.1.5.dist-info/WHEEL
directadmin_cli-0.1.5.dist-info/licenses/LICENSE
directadmin_cli-0.1.5.dist-info/RECORD
