Metadata-Version: 2.3
Name: directadmin-cli
Version: 0.1.5
Summary: DirectAdmin Python CommandLine tools
Project-URL: Homepage, https://github.com/Miladkhoshdel/directadmin-cli
Project-URL: Issues, https://github.com/Miladkhoshdel/directadmin-cli/issues
Author-email: Milad Khoshdel <miladkhoshdel@gmail.com>
Maintainer-email: Milad Khoshdel <miladkhoshdel@gmail.com>
License: MIT License
License-File: LICENSE
Keywords: da,directadmin
Requires-Python: >=3.8
Requires-Dist: requests
